thonnycontrib/thonny_black_format/__init__.py
thonny_black_format-0.0.4.dist-info/LICENSE
thonny_black_format-0.0.4.dist-info/METADATA
thonny_black_format-0.0.4.dist-info/WHEEL
thonny_black_format-0.0.4.dist-info/top_level.txt
thonny_black_format-0.0.4.dist-info/RECORD
