Metadata-Version: 2.1
Name: thonny-black-format
Version: 0.0.4
Summary: A plugin to format your python code with Black in Thonny IDE.
Home-page: https://github.com/Franccisco/thonny-black-code-format
Author: Franccisco
License: UNKNOWN
Platform: UNKNOWN
Classifier: Programming Language :: Python :: 3.7
Classifier: License :: OSI Approved :: MIT License
Classifier: Operating System :: OS Independent
Requires-Python: >=3.7
Requires-Dist: thonny (>=3.0.0)
Requires-Dist: black
